{
  "provider_id": "procar",
  "provider_name": "Procar",
  "snapshot_date": "2026-06-26",
  "timezone": "America/Bogota",
  "website": "https://procar.com.co/",
  "catalog_root_url": "https://procar.com.co/categoria-producto/llantas/auto/",
  "extraction_mode": "live_seeded_public_catalog_refresh",
  "notes": [
    "Extraction is limited to autos surfaces only; motos and heavy-duty lines are intentionally excluded.",
    "Public data remains partial and should be treated as supplier-verification support."
  ],
  "products": [
    {
      "item_type": "category",
      "provider_type": "category_only",
      "title": "Auto",
      "product_name": null,
      "detail_url": "https://procar.com.co/categoria-producto/llantas/auto/",
      "product_url": null,
      "category_name": "Auto",
      "subcategory_name": null,
      "brand": null,
      "reference": null,
      "sku": null,
      "supplier_item_code": null,
      "description": null,
      "vehicle_scope": null,
      "image_url": null,
      "source_page_url": "https://procar.com.co/categoria-producto/llantas/auto/",
      "page_number": 1,
      "match_type": "category_only",
      "match_confidence": "medium",
      "requires_manual_confirmation": true,
      "searchable_tokens": [
        "auto"
      ]
    },
    {
      "item_type": "product",
      "provider_type": "product_catalog",
      "title": null,
      "product_name": "GALLOPRO H/T",
      "detail_url": "https://procar.com.co/producto/gallopro-h-t/",
      "product_url": "https://procar.com.co/producto/gallopro-h-t/",
      "category_name": null,
      "subcategory_name": null,
      "brand": "",
      "reference": null,
      "sku": null,
      "supplier_item_code": null,
      "description": null,
      "vehicle_scope": "Autos",
      "image_url": null,
      "source_page_url": "https://procar.com.co/producto/gallopro-h-t/",
      "page_number": 1,
      "match_type": "category_only",
      "match_confidence": "medium",
      "requires_manual_confirmation": true,
      "searchable_tokens": [
        "gallopro",
        "autos"
      ]
    },
    {
      "item_type": "category",
      "provider_type": "category_only",
      "title": "Llantas",
      "product_name": null,
      "detail_url": "https://procar.com.co/categoria-producto/llantas/",
      "product_url": null,
      "category_name": "Llantas",
      "subcategory_name": null,
      "brand": null,
      "reference": null,
      "sku": null,
      "supplier_item_code": null,
      "description": null,
      "vehicle_scope": null,
      "image_url": null,
      "source_page_url": "https://procar.com.co/categoria-producto/llantas/",
      "page_number": 1,
      "match_type": "category_only",
      "match_confidence": "medium",
      "requires_manual_confirmation": true,
      "searchable_tokens": [
        "llantas"
      ]
    },
    {
      "item_type": "category",
      "provider_type": "category_only",
      "title": "FILTROS",
      "product_name": null,
      "detail_url": "https://procar.com.co/categoria-producto/filtros/",
      "product_url": null,
      "category_name": "FILTROS",
      "subcategory_name": null,
      "brand": null,
      "reference": null,
      "sku": null,
      "supplier_item_code": null,
      "description": null,
      "vehicle_scope": null,
      "image_url": null,
      "source_page_url": "https://procar.com.co/categoria-producto/filtros/",
      "page_number": 1,
      "match_type": "category_only",
      "match_confidence": "medium",
      "requires_manual_confirmation": true,
      "searchable_tokens": [
        "filtros"
      ]
    },
    {
      "item_type": "category",
      "provider_type": "category_only",
      "title": "LUBRICANTES",
      "product_name": null,
      "detail_url": "https://procar.com.co/categoria-producto/lubricantes/",
      "product_url": null,
      "category_name": "LUBRICANTES",
      "subcategory_name": null,
      "brand": null,
      "reference": null,
      "sku": null,
      "supplier_item_code": null,
      "description": null,
      "vehicle_scope": null,
      "image_url": null,
      "source_page_url": "https://procar.com.co/categoria-producto/lubricantes/",
      "page_number": 1,
      "match_type": "category_only",
      "match_confidence": "medium",
      "requires_manual_confirmation": true,
      "searchable_tokens": [
        "lubricantes"
      ]
    },
    {
      "item_type": "category",
      "provider_type": "category_only",
      "title": "OTROS PRODUCTOS",
      "product_name": null,
      "detail_url": "https://procar.com.co/categoria-producto/otros-productos/",
      "product_url": null,
      "category_name": "OTROS PRODUCTOS",
      "subcategory_name": null,
      "brand": null,
      "reference": null,
      "sku": null,
      "supplier_item_code": null,
      "description": null,
      "vehicle_scope": null,
      "image_url": null,
      "source_page_url": "https://procar.com.co/categoria-producto/otros-productos/",
      "page_number": 1,
      "match_type": "category_only",
      "match_confidence": "medium",
      "requires_manual_confirmation": true,
      "searchable_tokens": [
        "otros",
        "productos"
      ]
    },
    {
      "item_type": "product",
      "provider_type": "product_catalog",
      "title": null,
      "product_name": "ECOLANDER",
      "detail_url": "https://procar.com.co/producto/ecolander-2/",
      "product_url": "https://procar.com.co/producto/ecolander-2/",
      "category_name": null,
      "subcategory_name": null,
      "brand": "",
      "reference": null,
      "sku": null,
      "supplier_item_code": null,
      "description": null,
      "vehicle_scope": "Autos",
      "image_url": null,
      "source_page_url": "https://procar.com.co/producto/ecolander-2/",
      "page_number": 1,
      "match_type": "category_only",
      "match_confidence": "medium",
      "requires_manual_confirmation": true,
      "searchable_tokens": [
        "ecolander",
        "autos"
      ]
    },
    {
      "item_type": "product",
      "provider_type": "product_catalog",
      "title": null,
      "product_name": "ECOSAVER",
      "detail_url": "https://procar.com.co/producto/ecosaver-2/",
      "product_url": "https://procar.com.co/producto/ecosaver-2/",
      "category_name": null,
      "subcategory_name": null,
      "brand": "",
      "reference": null,
      "sku": null,
      "supplier_item_code": null,
      "description": null,
      "vehicle_scope": "Autos",
      "image_url": null,
      "source_page_url": "https://procar.com.co/producto/ecosaver-2/",
      "page_number": 1,
      "match_type": "category_only",
      "match_confidence": "medium",
      "requires_manual_confirmation": true,
      "searchable_tokens": [
        "ecosaver",
        "autos"
      ]
    },
    {
      "item_type": "product",
      "provider_type": "product_catalog",
      "title": null,
      "product_name": "EFFIVAN",
      "detail_url": "https://procar.com.co/producto/effivan-2/",
      "product_url": "https://procar.com.co/producto/effivan-2/",
      "category_name": null,
      "subcategory_name": null,
      "brand": "",
      "reference": null,
      "sku": null,
      "supplier_item_code": null,
      "description": null,
      "vehicle_scope": "Autos",
      "image_url": null,
      "source_page_url": "https://procar.com.co/producto/effivan-2/",
      "page_number": 1,
      "match_type": "category_only",
      "match_confidence": "medium",
      "requires_manual_confirmation": true,
      "searchable_tokens": [
        "effivan",
        "autos"
      ]
    },
    {
      "item_type": "product",
      "provider_type": "product_catalog",
      "title": null,
      "product_name": "LY166",
      "detail_url": "https://procar.com.co/producto/ly166/",
      "product_url": "https://procar.com.co/producto/ly166/",
      "category_name": null,
      "subcategory_name": null,
      "brand": "",
      "reference": null,
      "sku": null,
      "supplier_item_code": null,
      "description": null,
      "vehicle_scope": "Autos",
      "image_url": null,
      "source_page_url": "https://procar.com.co/producto/ly166/",
      "page_number": 1,
      "match_type": "category_only",
      "match_confidence": "medium",
      "requires_manual_confirmation": true,
      "searchable_tokens": [
        "ly166",
        "autos"
      ]
    },
    {
      "item_type": "product",
      "provider_type": "product_catalog",
      "title": null,
      "product_name": "LY688",
      "detail_url": "https://procar.com.co/producto/ly688/",
      "product_url": "https://procar.com.co/producto/ly688/",
      "category_name": null,
      "subcategory_name": null,
      "brand": "",
      "reference": null,
      "sku": null,
      "supplier_item_code": null,
      "description": null,
      "vehicle_scope": "Autos",
      "image_url": null,
      "source_page_url": "https://procar.com.co/producto/ly688/",
      "page_number": 1,
      "match_type": "category_only",
      "match_confidence": "medium",
      "requires_manual_confirmation": true,
      "searchable_tokens": [
        "ly688",
        "autos"
      ]
    },
    {
      "item_type": "product",
      "provider_type": "product_catalog",
      "title": null,
      "product_name": "P-309",
      "detail_url": "https://procar.com.co/producto/p-309/",
      "product_url": "https://procar.com.co/producto/p-309/",
      "category_name": null,
      "subcategory_name": null,
      "brand": "",
      "reference": null,
      "sku": null,
      "supplier_item_code": null,
      "description": null,
      "vehicle_scope": "Autos",
      "image_url": null,
      "source_page_url": "https://procar.com.co/producto/p-309/",
      "page_number": 1,
      "match_type": "category_only",
      "match_confidence": "medium",
      "requires_manual_confirmation": true,
      "searchable_tokens": [
        "309",
        "autos"
      ]
    },
    {
      "item_type": "product",
      "provider_type": "product_catalog",
      "title": null,
      "product_name": "P-609",
      "detail_url": "https://procar.com.co/producto/p-609/",
      "product_url": "https://procar.com.co/producto/p-609/",
      "category_name": null,
      "subcategory_name": null,
      "brand": "",
      "reference": null,
      "sku": null,
      "supplier_item_code": null,
      "description": null,
      "vehicle_scope": "Autos",
      "image_url": null,
      "source_page_url": "https://procar.com.co/producto/p-609/",
      "page_number": 1,
      "match_type": "category_only",
      "match_confidence": "medium",
      "requires_manual_confirmation": true,
      "searchable_tokens": [
        "609",
        "autos"
      ]
    },
    {
      "item_type": "product",
      "provider_type": "product_catalog",
      "title": null,
      "product_name": "X.SPIDER A/S",
      "detail_url": "https://procar.com.co/producto/x-spider-a-s/",
      "product_url": "https://procar.com.co/producto/x-spider-a-s/",
      "category_name": null,
      "subcategory_name": null,
      "brand": "",
      "reference": null,
      "sku": null,
      "supplier_item_code": null,
      "description": null,
      "vehicle_scope": "Autos",
      "image_url": null,
      "source_page_url": "https://procar.com.co/producto/x-spider-a-s/",
      "page_number": 1,
      "match_type": "category_only",
      "match_confidence": "medium",
      "requires_manual_confirmation": true,
      "searchable_tokens": [
        "spider",
        "autos"
      ]
    },
    {
      "item_type": "product",
      "provider_type": "product_catalog",
      "title": null,
      "product_name": "ZEALION",
      "detail_url": "https://procar.com.co/producto/zealion/",
      "product_url": "https://procar.com.co/producto/zealion/",
      "category_name": null,
      "subcategory_name": null,
      "brand": "",
      "reference": null,
      "sku": null,
      "supplier_item_code": null,
      "description": null,
      "vehicle_scope": "Autos",
      "image_url": null,
      "source_page_url": "https://procar.com.co/producto/zealion/",
      "page_number": 1,
      "match_type": "category_only",
      "match_confidence": "medium",
      "requires_manual_confirmation": true,
      "searchable_tokens": [
        "zealion",
        "autos"
      ]
    },
    {
      "item_type": "product",
      "provider_type": "product_catalog",
      "title": null,
      "product_name": "DX640",
      "detail_url": "https://procar.com.co/producto/dx640/",
      "product_url": "https://procar.com.co/producto/dx640/",
      "category_name": null,
      "subcategory_name": null,
      "brand": "",
      "reference": null,
      "sku": null,
      "supplier_item_code": null,
      "description": null,
      "vehicle_scope": "Autos",
      "image_url": null,
      "source_page_url": "https://procar.com.co/producto/dx640/",
      "page_number": 1,
      "match_type": "category_only",
      "match_confidence": "medium",
      "requires_manual_confirmation": true,
      "searchable_tokens": [
        "dx640",
        "autos"
      ]
    },
    {
      "item_type": "product",
      "provider_type": "product_catalog",
      "title": null,
      "product_name": "DX240",
      "detail_url": "https://procar.com.co/producto/dx240/",
      "product_url": "https://procar.com.co/producto/dx240/",
      "category_name": null,
      "subcategory_name": null,
      "brand": "",
      "reference": null,
      "sku": null,
      "supplier_item_code": null,
      "description": null,
      "vehicle_scope": "Autos",
      "image_url": null,
      "source_page_url": "https://procar.com.co/producto/dx240/",
      "page_number": 1,
      "match_type": "category_only",
      "match_confidence": "medium",
      "requires_manual_confirmation": true,
      "searchable_tokens": [
        "dx240",
        "autos"
      ]
    },
    {
      "item_type": "product",
      "provider_type": "product_catalog",
      "title": null,
      "product_name": "DX390",
      "detail_url": "https://procar.com.co/producto/dx390/",
      "product_url": "https://procar.com.co/producto/dx390/",
      "category_name": null,
      "subcategory_name": null,
      "brand": "",
      "reference": null,
      "sku": null,
      "supplier_item_code": null,
      "description": null,
      "vehicle_scope": "Autos",
      "image_url": null,
      "source_page_url": "https://procar.com.co/producto/dx390/",
      "page_number": 1,
      "match_type": "category_only",
      "match_confidence": "medium",
      "requires_manual_confirmation": true,
      "searchable_tokens": [
        "dx390",
        "autos"
      ]
    },
    {
      "item_type": "product",
      "provider_type": "product_catalog",
      "title": null,
      "product_name": "P307",
      "detail_url": "https://procar.com.co/producto/p307/",
      "product_url": "https://procar.com.co/producto/p307/",
      "category_name": null,
      "subcategory_name": null,
      "brand": null,
      "reference": null,
      "sku": null,
      "supplier_item_code": null,
      "description": null,
      "vehicle_scope": "Autos",
      "image_url": null,
      "source_page_url": "https://procar.com.co/producto/p307/",
      "page_number": 1,
      "match_type": "category_only",
      "match_confidence": "medium",
      "requires_manual_confirmation": true,
      "searchable_tokens": [
        "p307",
        "autos"
      ]
    },
    {
      "item_type": "product",
      "provider_type": "product_catalog",
      "title": null,
      "product_name": "P607",
      "detail_url": "https://procar.com.co/producto/p607/",
      "product_url": "https://procar.com.co/producto/p607/",
      "category_name": null,
      "subcategory_name": null,
      "brand": null,
      "reference": null,
      "sku": null,
      "supplier_item_code": null,
      "description": null,
      "vehicle_scope": "Autos",
      "image_url": null,
      "source_page_url": "https://procar.com.co/producto/p607/",
      "page_number": 1,
      "match_type": "category_only",
      "match_confidence": "medium",
      "requires_manual_confirmation": true,
      "searchable_tokens": [
        "p607",
        "autos"
      ]
    },
    {
      "item_type": "product",
      "provider_type": "product_catalog",
      "title": null,
      "product_name": "PROTOURA SPORT",
      "detail_url": "https://procar.com.co/producto/protoura-sport/",
      "product_url": "https://procar.com.co/producto/protoura-sport/",
      "category_name": null,
      "subcategory_name": null,
      "brand": "",
      "reference": null,
      "sku": null,
      "supplier_item_code": null,
      "description": null,
      "vehicle_scope": "Autos",
      "image_url": null,
      "source_page_url": "https://procar.com.co/producto/protoura-sport/",
      "page_number": 1,
      "match_type": "category_only",
      "match_confidence": "medium",
      "requires_manual_confirmation": true,
      "searchable_tokens": [
        "protoura",
        "sport",
        "autos"
      ]
    },
    {
      "item_type": "product",
      "provider_type": "product_catalog",
      "title": null,
      "product_name": "DREAMLAND R/T",
      "detail_url": "https://procar.com.co/producto/dreamland-r-t/",
      "product_url": "https://procar.com.co/producto/dreamland-r-t/",
      "category_name": null,
      "subcategory_name": null,
      "brand": "",
      "reference": null,
      "sku": null,
      "supplier_item_code": null,
      "description": null,
      "vehicle_scope": "Autos",
      "image_url": null,
      "source_page_url": "https://procar.com.co/producto/dreamland-r-t/",
      "page_number": 1,
      "match_type": "category_only",
      "match_confidence": "medium",
      "requires_manual_confirmation": true,
      "searchable_tokens": [
        "dreamland",
        "autos"
      ]
    },
    {
      "item_type": "product",
      "provider_type": "product_catalog",
      "title": null,
      "product_name": "MAXATRAVES M/T",
      "detail_url": "https://procar.com.co/producto/maxatraves-m-t/",
      "product_url": "https://procar.com.co/producto/maxatraves-m-t/",
      "category_name": null,
      "subcategory_name": null,
      "brand": "",
      "reference": null,
      "sku": null,
      "supplier_item_code": null,
      "description": null,
      "vehicle_scope": "Autos",
      "image_url": null,
      "source_page_url": "https://procar.com.co/producto/maxatraves-m-t/",
      "page_number": 1,
      "match_type": "category_only",
      "match_confidence": "medium",
      "requires_manual_confirmation": true,
      "searchable_tokens": [
        "maxatraves",
        "autos"
      ]
    }
  ]
}